mempy/__init__.py
mempy/fit.py
mempy/input_data.py
mempy/model.py
mempy/survival_models.py
mempyguts-1.6.0.dist-info/licenses/LICENSE
mempyguts-1.6.0.dist-info/METADATA
mempyguts-1.6.0.dist-info/WHEEL
mempyguts-1.6.0.dist-info/top_level.txt
mempyguts-1.6.0.dist-info/RECORD
