Metadata-Version: 2.4
Name: mempyguts
Version: 1.6.0
Summary: memPyGUTS is a python package for fitting GUTS models to survival data, from ecotoxicology experiments, developed at the Osnabrück University, Germany
Author-email: Vincent Hundertmark <vhundertmark@uni-osnabrueck.de>, Leonhard Bürger <leonhard.buerger@uni-osnabrueck.de>
License:                     GNU AFFERO GENERAL PUBLIC LICENSE
Project-URL: Homepage, https://gitlab.uni-osnabrueck.de/memuos/mempyguts
Project-URL: Issue Tracker, https://gitlab.uni-osnabrueck.de/memuos/mempyguts/issues
Classifier: Development Status :: 4 - Beta
Classifier: Programming Language :: Python :: 3
Classifier: Natural Language :: English
Classifier: License :: OSI Approved :: GNU General Public License v3 (GPLv3)
Classifier: Operating System :: OS Independent
Classifier: Topic :: Scientific/Engineering :: Bio-Informatics
Requires-Python: >=3.11
License-File: LICENSE
Requires-Dist: corner==2.2.2
Requires-Dist: emcee==3.1.6
Requires-Dist: lmfit==1.3.1
Requires-Dist: matplotlib>=3.7
Requires-Dist: numpy<2.0.0,>=1.24
Requires-Dist: openpyxl==3.1.3
Requires-Dist: pandas>=2.0
Requires-Dist: pillow==10.3.0
Requires-Dist: scipy>=1.10
Requires-Dist: seaborn==0.13.2
Requires-Dist: tabulate==0.9.0
Requires-Dist: tqdm>=4.65.0
Requires-Dist: ipykernel
Provides-Extra: dev
Requires-Dist: pytest; extra == "dev"
Requires-Dist: pre-commit; extra == "dev"
Provides-Extra: pymob
Requires-Dist: guts-base>=0.8.5; extra == "pymob"
Dynamic: license-file
